monobd/__init__.py
monobd/__version__.py
monobd/common/__init__.py
monobd/common/model.py
monobd/models/__init__.py
monobd/models/example.py
monobd/parts/__init__.py
monobd/parts/example.py
monobd/py.typed
monobd/utils/__init__.py
monobd/utils/bdview.py
monobd-0.0.1a1.dist-info/LICENSE
monobd-0.0.1a1.dist-info/METADATA
monobd-0.0.1a1.dist-info/WHEEL
monobd-0.0.1a1.dist-info/entry_points.txt
monobd-0.0.1a1.dist-info/RECORD
