Metadata-Version: 2.3
Name: monobd
Version: 0.0.1a1
Summary: Monorepository of build123d models
License: GPL-3.0-or-later
Author: Stephen Kent
Author-email: smkent@smkent.net
Requires-Python: >=3.10,<3.13
Classifier: Development Status :: 1 - Planning
Classifier: Operating System :: OS Independent
Classifier: Topic :: Software Development :: Libraries :: Python Modules
Classifier: Typing :: Typed
Requires-Dist: build123d (>=0.8.0,<0.9.0)
Requires-Dist: cadquery (>=2.5.2,<3.0.0)
